{
  "source": "seitas",
  "title": "seitas",
  "status": "full-read-auto-pass-1",
  "pages": 6,
  "primaryCategories": [
    "core_rule",
    "combat",
    "power_magic",
    "creature_npc"
  ],
  "parts": [
    {
      "id": "seitas-por-antonio-augusto-shaftiel-orifiel-hotmail-com-1",
      "name": "Por Antônio Augusto Shaftiel (orifiel@hotmail.com)",
      "category": "power_magic",
      "pages": [
        [
          1,
          6
        ]
      ],
      "summary": "Por Antônio Augusto Shaftiel (orifiel@hotmail.com) Autor de Entre Anjos e Demônios, Assassino de almas e Busca por Sangue Seitas do Céu e do Inferno Seitas Celestiais A Inquisição Celestial Fundada há cerca de seiscentos anos, a Inquisição Celestial é hoje uma das instituições mais fortes e perigosas da Cidade de Prata. Ela é temida por anjos, sejam estes fi...",
      "entityRefs": []
    }
  ]
}
